sagemaker_studio_cli/__init__.py
sagemaker_studio_cli/install.sh
sagemaker_studio_cli/_test/__init__.py
sagemaker_studio_cli/_test/cli_test.py
sagemaker_studio_cli/command/__init__.py
sagemaker_studio_cli/command/api_client.py
sagemaker_studio_cli/command/utils.py
sagemaker_studio_cli/command/config/__init__.py
sagemaker_studio_cli/command/config/global_config.py
sagemaker_studio_cli/command/credentials/__init__.py
sagemaker_studio_cli/command/execution/__init__.py
sagemaker_studio_cli/command/git/__init__.py
sagemaker_studio_cli/command/project/__init__.py
sagemaker_studio_cli-1.0.7.dist-info/licenses/LICENSE
sagemaker_studio_cli-1.0.7.dist-info/licenses/NOTICE
sagemaker_studio_cli-1.0.7.dist-info/METADATA
sagemaker_studio_cli-1.0.7.dist-info/WHEEL
sagemaker_studio_cli-1.0.7.dist-info/entry_points.txt
sagemaker_studio_cli-1.0.7.dist-info/top_level.txt
sagemaker_studio_cli-1.0.7.dist-info/zip-safe
sagemaker_studio_cli-1.0.7.dist-info/RECORD
